aiogram_dialog_manager/__init__.py
aiogram_dialog_manager/dialog.py
aiogram_dialog_manager/manager.py
aiogram_dialog_manager/filter/__init__.py
aiogram_dialog_manager/filter/access.py
aiogram_dialog_manager/filter/button.py
aiogram_dialog_manager/filter/data.py
aiogram_dialog_manager/filter/dialog.py
aiogram_dialog_manager/filter/state.py
aiogram_dialog_manager/instance/__init__.py
aiogram_dialog_manager/instance/button.py
aiogram_dialog_manager/instance/menu.py
aiogram_dialog_manager/instance/message.py
aiogram_dialog_manager/prototype/__init__.py
aiogram_dialog_manager/prototype/button.py
aiogram_dialog_manager/prototype/menu.py
aiogram_dialog_manager/storage/__init__.py
aiogram_dialog_manager/storage/base.py
aiogram_dialog_manager/storage/memory.py
aiogram_dialog_manager/storage/redis.py
aiogram_dialog_manager-1.0.1.dist-info/METADATA
aiogram_dialog_manager-1.0.1.dist-info/WHEEL
aiogram_dialog_manager-1.0.1.dist-info/top_level.txt
aiogram_dialog_manager-1.0.1.dist-info/RECORD
